{
    "DEN": {
        "info": {
            "record": "43-25",
            "standing": "3rd in West",
            "coach": "Michael Malone (43-25)",
            "gm": "Calvin Booth",
            "preseason_odds": "+750"
        },
        "players": [
            "Christian Braun",
            "Michael Porter Jr.",
            "Nikola Jokić",
            "Jamal Murray",
            "Russell Westbrook",
            "Julian Strawther",
            "Peyton Watson",
            "Zeke Nnaji",
            "DeAndre Jordan",
            "Hunter Tyson",
            "Aaron Gordon",
            "Jalen Pickett",
            "Trey Alexander",
            "PJ Hall",
            "Dario Šarić",
            "Spencer Jones",
            "Vlatko Čančar",
            "DaRon Holmes"
        ],
        "injuries": [
            {
                "Player": "Aaron Gordon",
                "Team": "Denver Nuggets",
                "Update": "Sat, Mar 15, 2025",
                "Description": "Day To Day (Calf) - Gordon did not play on Saturday's (Mar. 15) game versus the Wizards."
            },
            {
                "Player": "DaRon Holmes",
                "Team": "Denver Nuggets",
                "Update": "Sun, Feb 23, 2025",
                "Description": "Out For Season (Achilles) - Nuggets HC Michael Malone said that Holmes was able to participate in portions of Wednesday's (Feb. 19) practice, as per Brendan Vogt of TheDNVR.com reports."
            },
            {
                "Player": "Julian Strawther",
                "Team": "Denver Nuggets",
                "Update": "Tue, Mar 4, 2025",
                "Description": "Out (Knee) - The Nuggets announced on Tuesday (Mar. 4) that Strawther will be re-evaluated in four weeks, per Romi Bean of CBS News Colorado."
            }
        ],
        "team_stats": {
            "Team": {
                "G": "68",
                "MP": "16445",
                "FG": "3108",
                "FGA": "6134",
                "FG%": ".507",
                "3P": "827",
                "3PA": "2165",
                "3P%": ".382",
                "2P": "2281",
                "2PA": "3969",
                "2P%": ".575",
                "FT": "1201",
                "FTA": "1549",
                "FT%": ".775",
                "ORB": "761",
                "DRB": "2343",
                "TRB": "3104",
                "AST": "2117",
                "STL": "551",
                "BLK": "324",
                "TOV": "960",
                "PF": "1196",
                "PTS": "8244"
            },
            "Team/G": {
                "G": "",
                "MP": "241.8",
                "FG": "45.7",
                "FGA": "90.2",
                "FG%": ".507",
                "3P": "12.2",
                "3PA": "31.8",
                "3P%": ".382",
                "2P": "33.5",
                "2PA": "58.4",
                "2P%": ".575",
                "FT": "17.7",
                "FTA": "22.8",
                "FT%": ".775",
                "ORB": "11.2",
                "DRB": "34.5",
                "TRB": "45.6",
                "AST": "31.1",
                "STL": "8.1",
                "BLK": "4.8",
                "TOV": "14.1",
                "PF": "17.6",
                "PTS": "121.2"
            },
            "Lg Rank": {
                "G": "",
                "MP": "5",
                "FG": "1",
                "FGA": "11",
                "FG%": "1",
                "3P": "28",
                "3PA": "30",
                "3P%": "3",
                "2P": "1",
                "2PA": "1",
                "2P%": "2",
                "FT": "7",
                "FTA": "7",
                "FT%": "20",
                "ORB": "11",
                "DRB": "4",
                "TRB": "5",
                "AST": "1",
                "STL": "15",
                "BLK": "18",
                "TOV": "15",
                "PF": "6",
                "PTS": "3"
            },
            "Year/Year": {
                "G": "",
                "MP": "0.6%",
                "FG": "3.8%",
                "FGA": "1.6%",
                "FG%": "+.011",
                "3P": "4.1%",
                "3PA": "2.0%",
                "3P%": "+.008",
                "2P": "3.7%",
                "2PA": "1.4%",
                "2P%": "+.013",
                "FT": "16.8%",
                "FTA": "14.7%",
                "FT%": "+.014",
                "ORB": "4.2%",
                "DRB": "2.3%",
                "TRB": "2.7%",
                "AST": "5.7%",
                "STL": "13.6%",
                "BLK": "-14.5%",
                "TOV": "11.7%",
                "PF": "-3.1%",
                "PTS": "5.6%"
            },
            "Opponent": {
                "G": "68",
                "MP": "16445",
                "FG": "2948",
                "FGA": "6338",
                "FG%": ".465",
                "3P": "958",
                "3PA": "2623",
                "3P%": ".365",
                "2P": "1990",
                "2PA": "3715",
                "2P%": ".536",
                "FT": "1094",
                "FTA": "1393",
                "FT%": ".785",
                "ORB": "798",
                "DRB": "2093",
                "TRB": "2891",
                "AST": "1989",
                "STL": "600",
                "BLK": "353",
                "TOV": "891",
                "PF": "1283",
                "PTS": "7948"
            },
            "Opponent/G": {
                "G": "",
                "MP": "241.8",
                "FG": "43.4",
                "FGA": "93.2",
                "FG%": ".465",
                "3P": "14.1",
                "3PA": "38.6",
                "3P%": ".365",
                "2P": "29.3",
                "2PA": "54.6",
                "2P%": ".536",
                "FT": "16.1",
                "FTA": "20.5",
                "FT%": ".785",
                "ORB": "11.7",
                "DRB": "30.8",
                "TRB": "42.5",
                "AST": "29.3",
                "STL": "8.8",
                "BLK": "5.2",
                "TOV": "13.1",
                "PF": "18.9",
                "PTS": "116.9"
            },
            "Opp Lg Rank": {
                "G": "",
                "MP": "5",
                "FG": "24",
                "FGA": "29",
                "FG%": "13",
                "3P": "25",
                "3PA": "21",
                "3P%": "22",
                "2P": "23",
                "2PA": "28",
                "2P%": "11",
                "FT": "7",
                "FTA": "7",
                "FT%": "19",
                "ORB": "22",
                "DRB": "1",
                "TRB": "5",
                "AST": "30",
                "STL": "22",
                "BLK": "20",
                "TOV": "25",
                "PF": "14",
                "PTS": "25"
            },
            "Opp Year/Year": {
                "G": "",
                "MP": "0.6%",
                "FG": "6.7%",
                "FGA": "6.0%",
                "FG%": "+.003",
                "3P": "25.7%",
                "3PA": "22.3%",
                "3P%": "+.010",
                "2P": "-0.6%",
                "2PA": "-3.1%",
                "2P%": "+.014",
                "FT": "-6.0%",
                "FTA": "-7.7%",
                "FT%": "+.014",
                "ORB": "7.6%",
                "DRB": "-1.9%",
                "TRB": "0.6%",
                "AST": "13.8%",
                "STL": "25.2%",
                "BLK": "8.0%",
                "TOV": "6.0%",
                "PF": "5.5%",
                "PTS": "6.6%"
            },
            "Misc Team": {
                "W": "43",
                "L": "25",
                "PW": "43",
                "PL": "25",
                "MOV": "4.35",
                "SOS": "-0.11",
                "SRS": "4.24",
                "ORtg": "120.2",
                "DRtg": "115.9",
                "Pace": "100.1",
                "FTr": ".253",
                "3PAr": ".353",
                "eFG%": ".541",
                "TOV%": "11.4",
                "ORB%": "26.7",
                "FT/FGA": ".173",
                "DRB%": "74.6",
                "Arena": "Ball Arena",
                "Attendance": "672,451"
            },
            "Misc Lg Rank": {
                "W": "4",
                "L": "23",
                "PW": "7",
                "PL": "7",
                "MOV": "6",
                "SOS": "16",
                "SRS": "7",
                "ORtg": "2",
                "DRtg": "23",
                "Pace": "6",
                "FTr": "10",
                "3PAr": "30",
                "eFG%": "14",
                "TOV%": "26",
                "ORB%": "8",
                "FT/FGA": "4",
                "DRB%": "16",
                "Arena": "",
                "Attendance": "6"
            }
        },
        "image_url": "https://cdn.ssref.net/req/202502211/tlogo/bbr/DEN-2025.png",
        "last_update": "Mar 17 2025 22:32:20"
    }
}