{
    "PHI": {
        "info": {
            "record": "13-17",
            "standing": "11th in East",
            "coach": "Nick Nurse (13-17)",
            "gm": "Daryl Morey",
            "preseason_odds": "+1400"
        },
        "players": [
            "Kelly Oubre Jr.",
            "Guerschon Yabusele",
            "Caleb Martin",
            "Tyrese Maxey",
            "Andre Drummond",
            "KJ Martin",
            "Jared McCain",
            "Ricky Council IV",
            "Kyle Lowry",
            "Paul George",
            "Eric Gordon",
            "Adem Bona",
            "Reggie Jackson",
            "Joel Embiid",
            "Jeff Dowtin",
            "Justin Edwards",
            "Pete Nance"
        ],
        "injuries": [
            {
                "Player": "Andre Drummond",
                "Team": "Philadelphia 76ers",
                "Update": "Tue, Dec 31, 2024",
                "Description": "Day To Day (Toe) - The 76ers have listed Drummond as Questionable for Wednesday's (Jan. 1) game against the Kings."
            },
            {
                "Player": "Joel Embiid",
                "Team": "Philadelphia 76ers",
                "Update": "Tue, Dec 31, 2024",
                "Description": "Out (Rest) - The 76ers have listed Embiid as Out for Wednesday's (Jan. 1) game against the Kings."
            },
            {
                "Player": "Eric Gordon",
                "Team": "Philadelphia 76ers",
                "Update": "Tue, Dec 31, 2024",
                "Description": "Day To Day (Mouth) - The 76ers have listed Gordon as Questionable for Wednesday's (Jan. 1) game against the Kings."
            },
            {
                "Player": "Kyle Lowry",
                "Team": "Philadelphia 76ers",
                "Update": "Tue, Dec 31, 2024",
                "Description": "Day To Day (Hip) - The 76ers have listed Lowry as Questionable for Wednesday's (Jan. 1) game against the Kings."
            },
            {
                "Player": "KJ Martin",
                "Team": "Philadelphia 76ers",
                "Update": "Tue, Dec 31, 2024",
                "Description": "Out (Foot) - Martin will be re-evaluated in two weeks due to a stress reaction in his left foot, Adam Aaronson of PhillyVoice.com reports."
            },
            {
                "Player": "Jared McCain",
                "Team": "Philadelphia 76ers",
                "Update": "Tue, Dec 17, 2024",
                "Description": "Out (Meniscus) - The 76ers announced on Tuesday (Dec. 17) that McCain underwent successful surgery to repair a lateral meniscus tear and remains out indefinitely, per Tim Bontemps of ESPN.com."
            }
        ],
        "team_stats": {
            "Team": {
                "G": "30",
                "MP": "7275",
                "FG": "1145",
                "FGA": "2564",
                "FG%": ".447",
                "3P": "360",
                "3PA": "1066",
                "3P%": ".338",
                "2P": "785",
                "2PA": "1498",
                "2P%": ".524",
                "FT": "567",
                "FTA": "727",
                "FT%": ".780",
                "ORB": "312",
                "DRB": "888",
                "TRB": "1200",
                "AST": "653",
                "STL": "293",
                "BLK": "124",
                "TOV": "427",
                "PF": "611",
                "PTS": "3217"
            },
            "Team/G": {
                "G": "",
                "MP": "242.5",
                "FG": "38.2",
                "FGA": "85.5",
                "FG%": ".447",
                "3P": "12.0",
                "3PA": "35.5",
                "3P%": ".338",
                "2P": "26.2",
                "2PA": "49.9",
                "2P%": ".524",
                "FT": "18.9",
                "FTA": "24.2",
                "FT%": ".780",
                "ORB": "10.4",
                "DRB": "29.6",
                "TRB": "40.0",
                "AST": "21.8",
                "STL": "9.8",
                "BLK": "4.1",
                "TOV": "14.2",
                "PF": "20.4",
                "PTS": "107.2"
            },
            "Lg Rank": {
                "G": "",
                "MP": "28",
                "FG": "28",
                "FGA": "27",
                "FG%": "24",
                "3P": "22",
                "3PA": "23",
                "3P%": "25",
                "2P": "22",
                "2PA": "18",
                "2P%": "22",
                "FT": "5",
                "FTA": "4",
                "FT%": "17",
                "ORB": "19",
                "DRB": "30",
                "TRB": "29",
                "AST": "30",
                "STL": "3",
                "BLK": "27",
                "TOV": "11",
                "PF": "23",
                "PTS": "27"
            },
            "Year/Year": {
                "G": "",
                "MP": "0.5%",
                "FG": "-8.1%",
                "FGA": "-4.4%",
                "FG%": "-.018",
                "3P": "-0.8%",
                "3PA": "6.6%",
                "3P%": "-.025",
                "2P": "-11.0%",
                "2PA": "-10.9%",
                "2P%": "-.001",
                "FT": "-3.0%",
                "FTA": "2.7%",
                "FT%": "-.046",
                "ORB": "-5.9%",
                "DRB": "-7.2%",
                "TRB": "-6.9%",
                "AST": "-12.5%",
                "STL": "15.4%",
                "BLK": "-31.1%",
                "TOV": "18.6%",
                "PF": "0.1%",
                "PTS": "-6.4%"
            },
            "Opponent": {
                "G": "30",
                "MP": "7275",
                "FG": "1198",
                "FGA": "2511",
                "FG%": ".477",
                "3P": "395",
                "3PA": "1116",
                "3P%": ".354",
                "2P": "803",
                "2PA": "1395",
                "2P%": ".576",
                "FT": "518",
                "FTA": "644",
                "FT%": ".804",
                "ORB": "303",
                "DRB": "1011",
                "TRB": "1314",
                "AST": "778",
                "STL": "222",
                "BLK": "167",
                "TOV": "523",
                "PF": "609",
                "PTS": "3309"
            },
            "Opponent/G": {
                "G": "",
                "MP": "242.5",
                "FG": "39.9",
                "FGA": "83.7",
                "FG%": ".477",
                "3P": "13.2",
                "3PA": "37.2",
                "3P%": ".354",
                "2P": "26.8",
                "2PA": "46.5",
                "2P%": ".576",
                "FT": "17.3",
                "FTA": "21.5",
                "FT%": ".804",
                "ORB": "10.1",
                "DRB": "33.7",
                "TRB": "43.8",
                "AST": "25.9",
                "STL": "7.4",
                "BLK": "5.6",
                "TOV": "17.4",
                "PF": "20.3",
                "PTS": "110.3"
            },
            "Opp Lg Rank": {
                "G": "",
                "MP": "28",
                "FG": "6",
                "FGA": "3",
                "FG%": "25",
                "3P": "9",
                "3PA": "9",
                "3P%": "11",
                "2P": "9",
                "2PA": "1",
                "2P%": "30",
                "FT": "18",
                "FTA": "11",
                "FT%": "29",
                "ORB": "6",
                "DRB": "21",
                "TRB": "12",
                "AST": "13",
                "STL": "5",
                "BLK": "20",
                "TOV": "2",
                "PF": "7",
                "PTS": "9"
            },
            "Opp Year/Year": {
                "G": "",
                "MP": "0.5%",
                "FG": "-1.4%",
                "FGA": "-3.3%",
                "FG%": "+.009",
                "3P": "10.3%",
                "3PA": "10.3%",
                "3P%": "-.000",
                "2P": "-6.3%",
                "2PA": "-12.0%",
                "2P%": "+.035",
                "FT": "-7.1%",
                "FTA": "-8.6%",
                "FT%": "+.013",
                "ORB": "-8.3%",
                "DRB": "0.8%",
                "TRB": "-1.5%",
                "AST": "-0.8%",
                "STL": "19.9%",
                "BLK": "-9.3%",
                "TOV": "19.0%",
                "PF": "9.6%",
                "PTS": "-1.1%"
            },
            "Misc Team": {
                "W": "13",
                "L": "17",
                "PW": "12",
                "PL": "18",
                "MOV": "-3.07",
                "SOS": "0.06",
                "SRS": "-3.01",
                "ORtg": "109.8",
                "DRtg": "113.0",
                "Pace": "96.6",
                "FTr": ".284",
                "3PAr": ".416",
                "eFG%": ".556",
                "TOV%": "15.8",
                "ORB%": "23.6",
                "FT/FGA": ".206",
                "DRB%": "74.6",
                "Arena": "Wells Fargo Center",
                "Attendance": "277,941"
            },
            "Misc Lg Rank": {
                "W": "23",
                "L": "12",
                "PW": "23",
                "PL": "19",
                "MOV": "22",
                "SOS": "14",
                "SRS": "23",
                "ORtg": "24",
                "DRtg": "15",
                "Pace": "30",
                "FTr": "1",
                "3PAr": "16",
                "eFG%": "24",
                "TOV%": "3",
                "ORB%": "19",
                "FT/FGA": "20",
                "DRB%": "20",
                "Arena": "",
                "Attendance": "21"
            }
        },
        "image_url": "https://cdn.ssref.net/req/202412261/tlogo/bbr/PHI-2025.png",
        "last_update": "Jan 01 2025 22:32:12"
    }
}