{
    "SAC": {
        "info": {
            "record": "12-13",
            "standing": "12th in West",
            "coach": "Mike Brown (12-13)",
            "gm": "Monte McNair",
            "preseason_odds": "+6600"
        },
        "players": [
            "De'Aaron Fox",
            "Keegan Murray",
            "Domantas Sabonis",
            "Keon Ellis",
            "Kevin Huerter",
            "DeMar DeRozan",
            "Jordan McLaughlin",
            "Doug McDermott",
            "Malik Monk",
            "Trey Lyles",
            "Alex Len",
            "Colby Jones",
            "Isaac Jones",
            "Jae Crowder",
            "Orlando Robinson",
            "Isaiah Crawford",
            "Devin Carter"
        ],
        "injuries": [
            {
                "Player": "Devin Carter",
                "Team": "Sacramento Kings",
                "Update": "Mon, Nov 11, 2024",
                "Description": "Out (Shoulder) - Carter was cleared to participate in unrestricted shooting drills Monday, Matt George of ABC 10 Sacramento reports."
            },
            {
                "Player": "Isaac Jones",
                "Team": "Sacramento Kings",
                "Update": "Mon, Dec 9, 2024",
                "Description": "Day To Day (Illness) - Jones did not play in Sunday's (Dec. 8) game against Utah."
            },
            {
                "Player": "Trey Lyles",
                "Team": "Sacramento Kings",
                "Update": "Tue, Nov 26, 2024",
                "Description": "Out (Calf) - The Kings announced that Lyles has suffered a Grade 1 right calf strain and will re-evaluated in 3-4 weeks, Frankie Cartoscelli of KHTK Sactown Sports 1140 reports."
            }
        ],
        "team_stats": {
            "Team": {
                "G": "25",
                "MP": "6075",
                "FG": "1079",
                "FGA": "2220",
                "FG%": ".486",
                "3P": "302",
                "3PA": "873",
                "3P%": ".346",
                "2P": "777",
                "2PA": "1347",
                "2P%": ".577",
                "FT": "450",
                "FTA": "566",
                "FT%": ".795",
                "ORB": "247",
                "DRB": "832",
                "TRB": "1079",
                "AST": "646",
                "STL": "204",
                "BLK": "122",
                "TOV": "340",
                "PF": "506",
                "PTS": "2910"
            },
            "Team/G": {
                "G": "",
                "MP": "243.0",
                "FG": "43.2",
                "FGA": "88.8",
                "FG%": ".486",
                "3P": "12.1",
                "3PA": "34.9",
                "3P%": ".346",
                "2P": "31.1",
                "2PA": "53.9",
                "2P%": ".577",
                "FT": "18.0",
                "FTA": "22.6",
                "FT%": ".795",
                "ORB": "9.9",
                "DRB": "33.3",
                "TRB": "43.2",
                "AST": "25.8",
                "STL": "8.2",
                "BLK": "4.9",
                "TOV": "13.6",
                "PF": "20.2",
                "PTS": "116.4"
            },
            "Lg Rank": {
                "G": "",
                "MP": "2",
                "FG": "8",
                "FGA": "15",
                "FG%": "7",
                "3P": "21",
                "3PA": "24",
                "3P%": "21",
                "2P": "3",
                "2PA": "10",
                "2P%": "3",
                "FT": "11",
                "FTA": "13",
                "FT%": "7",
                "ORB": "21",
                "DRB": "14",
                "TRB": "18",
                "AST": "15",
                "STL": "17",
                "BLK": "18",
                "TOV": "8",
                "PF": "21",
                "PTS": "9"
            },
            "Year/Year": {
                "G": "",
                "MP": "0.4%",
                "FG": "-0.4%",
                "FGA": "-2.3%",
                "FG%": "+.009",
                "3P": "-15.9%",
                "3PA": "-11.0%",
                "3P%": "-.020",
                "2P": "7.3%",
                "2PA": "4.3%",
                "2P%": "+.016",
                "FT": "15.9%",
                "FTA": "8.6%",
                "FT%": "+.050",
                "ORB": "-8.8%",
                "DRB": "0.4%",
                "TRB": "-1.9%",
                "AST": "-8.8%",
                "STL": "7.1%",
                "BLK": "17.0%",
                "TOV": "3.5%",
                "PF": "1.7%",
                "PTS": "-0.1%"
            },
            "Opponent": {
                "G": "25",
                "MP": "6075",
                "FG": "1002",
                "FGA": "2182",
                "FG%": ".459",
                "3P": "375",
                "3PA": "994",
                "3P%": ".377",
                "2P": "627",
                "2PA": "1188",
                "2P%": ".528",
                "FT": "451",
                "FTA": "563",
                "FT%": ".801",
                "ORB": "249",
                "DRB": "795",
                "TRB": "1044",
                "AST": "640",
                "STL": "204",
                "BLK": "102",
                "TOV": "384",
                "PF": "485",
                "PTS": "2830"
            },
            "Opponent/G": {
                "G": "",
                "MP": "243.0",
                "FG": "40.1",
                "FGA": "87.3",
                "FG%": ".459",
                "3P": "15.0",
                "3PA": "39.8",
                "3P%": ".377",
                "2P": "25.1",
                "2PA": "47.5",
                "2P%": ".528",
                "FT": "18.0",
                "FTA": "22.5",
                "FT%": ".801",
                "ORB": "10.0",
                "DRB": "31.8",
                "TRB": "41.8",
                "AST": "25.6",
                "STL": "8.2",
                "BLK": "4.1",
                "TOV": "15.4",
                "PF": "19.4",
                "PTS": "113.2"
            },
            "Opp Lg Rank": {
                "G": "",
                "MP": "2",
                "FG": "8",
                "FGA": "8",
                "FG%": "9",
                "3P": "29",
                "3PA": "27",
                "3P%": "29",
                "2P": "2",
                "2PA": "4",
                "2P%": "9",
                "FT": "20",
                "FTA": "18",
                "FT%": "27",
                "ORB": "6",
                "DRB": "6",
                "TRB": "5",
                "AST": "12",
                "STL": "14",
                "BLK": "4",
                "TOV": "9",
                "PF": "15",
                "PTS": "17"
            },
            "Opp Year/Year": {
                "G": "",
                "MP": "0.4%",
                "FG": "-3.7%",
                "FGA": "0.6%",
                "FG%": "-.021",
                "3P": "14.5%",
                "3PA": "17.5%",
                "3P%": "-.010",
                "2P": "-12.1%",
                "2PA": "-10.2%",
                "2P%": "-.012",
                "FT": "-2.2%",
                "FTA": "-2.4%",
                "FT%": "+.001",
                "ORB": "9.3%",
                "DRB": "-4.8%",
                "TRB": "-1.8%",
                "AST": "-4.9%",
                "STL": "10.4%",
                "BLK": "-9.6%",
                "TOV": "10.6%",
                "PF": "5.8%",
                "PTS": "-1.4%"
            },
            "Misc Team": {
                "W": "12",
                "L": "13",
                "PW": "15",
                "PL": "10",
                "MOV": "3.20",
                "SOS": "-1.01",
                "SRS": "2.19",
                "ORtg": "116.5",
                "DRtg": "113.3",
                "Pace": "98.7",
                "FTr": ".255",
                "3PAr": ".393",
                "eFG%": ".545",
                "TOV%": "13.6",
                "ORB%": "23.7",
                "FT/FGA": ".207",
                "DRB%": "77.0",
                "Arena": "Golden 1 Center",
                "Attendance": "215,237"
            },
            "Misc Lg Rank": {
                "W": "14",
                "L": "12",
                "PW": "10",
                "PL": "13",
                "MOV": "11",
                "SOS": "25",
                "SRS": "14",
                "ORtg": "7",
                "DRtg": "13",
                "Pace": "16",
                "FTr": "13",
                "3PAr": "22",
                "eFG%": "18",
                "TOV%": "11",
                "ORB%": "17",
                "FT/FGA": "21",
                "DRB%": "5",
                "Arena": "",
                "Attendance": "14"
            }
        },
        "image_url": "https://cdn.ssref.net/req/202411271/tlogo/bbr/SAC-2025.png",
        "last_update": "Dec 11 2024 22:32:13"
    }
}