{
    "UTA": {
        "Tm": "UTA",
        "RRK": "1",
        "Name": "Utah Jazz",
        "img": "https://cdn.ssref.net/req/202312151/tlogo/bbr/UTA-2021.png",
        "standing": "Finished in West in 2021 in West in West",
        "last_update": "May 18 2024 21:37:02",
        "avg_grade": 86.36,
        "score": 95.04,
        "link": "https://www.basketball-reference.com/teams/2021/UTA.html",
        "rank": 1
    },
    "PHO": {
        "Tm": "PHO",
        "RRK": "2",
        "Name": "Phoenix Suns",
        "img": "https://cdn.ssref.net/req/202312151/tlogo/bbr/PHO-2021.png",
        "standing": "Finished in West in 2021 in West in West in West in Finals",
        "last_update": "May 18 2024 21:37:02",
        "avg_grade": 84.65,
        "score": 94.05,
        "link": "https://www.basketball-reference.com/teams/2021/PHO.html",
        "rank": 2
    },
    "BRK": {
        "Tm": "BRK",
        "RRK": "4",
        "Name": "Brooklyn Nets",
        "img": "https://cdn.ssref.net/req/202312151/tlogo/bbr/BRK-2021.png",
        "standing": "Finished in East in 2021 in East in East",
        "last_update": "May 18 2024 21:37:02",
        "avg_grade": 86.59,
        "score": 93.86,
        "link": "https://www.basketball-reference.com/teams/2021/BRK.html",
        "rank": 3
    },
    "PHI": {
        "Tm": "PHI",
        "RRK": "3",
        "Name": "Philadelphia 76ers",
        "img": "https://cdn.ssref.net/req/202312151/tlogo/bbr/PHI-2021.png",
        "standing": "Finished in East in 2021 in East in East",
        "last_update": "May 18 2024 21:37:02",
        "avg_grade": 83.92,
        "score": 93.39,
        "link": "https://www.basketball-reference.com/teams/2021/PHI.html",
        "rank": 4
    },
    "LAC": {
        "Tm": "LAC",
        "RRK": "6",
        "Name": "Los Angeles Clippers",
        "img": "https://cdn.ssref.net/req/202312151/tlogo/bbr/LAC-2021.png",
        "standing": "Finished in West in 2021 in West in West in West",
        "last_update": "May 18 2024 21:37:02",
        "avg_grade": 85.63,
        "score": 92.71,
        "link": "https://www.basketball-reference.com/teams/2021/LAC.html",
        "rank": 5
    },
    "DEN": {
        "Tm": "DEN",
        "RRK": "5",
        "Name": "Denver Nuggets",
        "img": "https://cdn.ssref.net/req/202312151/tlogo/bbr/DEN-2021.png",
        "standing": "Finished in West in 2021 in West in West",
        "last_update": "May 18 2024 21:37:02",
        "avg_grade": 83.26,
        "score": 92.34,
        "link": "https://www.basketball-reference.com/teams/2021/DEN.html",
        "rank": 6
    },
    "MIL": {
        "Tm": "MIL",
        "RRK": "7",
        "Name": "Milwaukee Bucks",
        "img": "https://cdn.ssref.net/req/202312151/tlogo/bbr/MIL-2021.png",
        "standing": "Finished in East in 2021 in East in East in East in Finals",
        "last_update": "May 18 2024 21:37:02",
        "avg_grade": 84.66,
        "score": 91.97,
        "link": "https://www.basketball-reference.com/teams/2021/MIL.html",
        "rank": 7
    },
    "DAL": {
        "Tm": "DAL",
        "RRK": "8",
        "Name": "Dallas Mavericks",
        "img": "https://cdn.ssref.net/req/202312151/tlogo/bbr/DAL-2021.png",
        "standing": "Finished in West in 2021 in West",
        "last_update": "May 18 2024 21:37:02",
        "avg_grade": 82.86,
        "score": 90.95,
        "link": "https://www.basketball-reference.com/teams/2021/DAL.html",
        "rank": 8
    },
    "LAL": {
        "Tm": "LAL",
        "RRK": "9",
        "Name": "Los Angeles Lakers",
        "img": "https://cdn.ssref.net/req/202312151/tlogo/bbr/LAL-2021.png",
        "standing": "Finished in West in 2021 in West",
        "last_update": "May 18 2024 21:37:02",
        "avg_grade": 83.08,
        "score": 90.61,
        "link": "https://www.basketball-reference.com/teams/2021/LAL.html",
        "rank": 9
    },
    "POR": {
        "Tm": "POR",
        "RRK": "10",
        "Name": "Portland Trail Blazers",
        "img": "https://cdn.ssref.net/req/202312151/tlogo/bbr/POR-2021.png",
        "standing": "Finished in West in 2021 in West",
        "last_update": "May 18 2024 21:37:02",
        "avg_grade": 82.69,
        "score": 90.06,
        "link": "https://www.basketball-reference.com/teams/2021/POR.html",
        "rank": 10
    },
    "ATL": {
        "Tm": "ATL",
        "RRK": "11",
        "Name": "Atlanta Hawks",
        "img": "https://cdn.ssref.net/req/202312151/tlogo/bbr/ATL-2021.png",
        "standing": "Finished in East in 2021 in East in East in East",
        "last_update": "May 18 2024 21:37:02",
        "avg_grade": 83.94,
        "score": 90.06,
        "link": "https://www.basketball-reference.com/teams/2021/ATL.html",
        "rank": 11
    },
    "NYK": {
        "Tm": "NYK",
        "RRK": "12",
        "Name": "New York Knicks",
        "img": "https://cdn.ssref.net/req/202312151/tlogo/bbr/NYK-2021.png",
        "standing": "Finished in East in 2021 in East",
        "last_update": "May 18 2024 21:37:02",
        "avg_grade": 83.2,
        "score": 89.4,
        "link": "https://www.basketball-reference.com/teams/2021/NYK.html",
        "rank": 12
    },
    "MIA": {
        "Tm": "MIA",
        "RRK": "13",
        "Name": "Miami Heat",
        "img": "https://cdn.ssref.net/req/202312151/tlogo/bbr/MIA-2021.png",
        "standing": "Finished in East in 2021 in East",
        "last_update": "May 18 2024 21:37:02",
        "avg_grade": 81.38,
        "score": 88.38,
        "link": "https://www.basketball-reference.com/teams/2021/MIA.html",
        "rank": 13
    },
    "GSW": {
        "Tm": "GSW",
        "RRK": "14",
        "Name": "Golden State Warriors",
        "img": "https://cdn.ssref.net/req/202312151/tlogo/bbr/GSW-2021.png",
        "standing": "Finished in West",
        "last_update": "May 18 2024 21:37:02",
        "avg_grade": 80.96,
        "score": 87.82,
        "link": "https://www.basketball-reference.com/teams/2021/GSW.html",
        "rank": 14
    },
    "MEM": {
        "Tm": "MEM",
        "RRK": "15",
        "Name": "Memphis Grizzlies",
        "img": "https://cdn.ssref.net/req/202312151/tlogo/bbr/MEM-2021.png",
        "standing": "Finished in West in 2021 in West",
        "last_update": "May 18 2024 21:37:02",
        "avg_grade": 82.2,
        "score": 87.81,
        "link": "https://www.basketball-reference.com/teams/2021/MEM.html",
        "rank": 15
    },
    "BOS": {
        "Tm": "BOS",
        "RRK": "16",
        "Name": "Boston Celtics",
        "img": "https://cdn.ssref.net/req/202312151/tlogo/bbr/BOS-2021.png",
        "standing": "Finished in East in 2021 in East",
        "last_update": "May 18 2024 21:37:02",
        "avg_grade": 82.92,
        "score": 87.64,
        "link": "https://www.basketball-reference.com/teams/2021/BOS.html",
        "rank": 16
    },
    "IND": {
        "Tm": "IND",
        "RRK": "18",
        "Name": "Indiana Pacers",
        "img": "https://cdn.ssref.net/req/202312151/tlogo/bbr/IND-2021.png",
        "standing": "Finished in East",
        "last_update": "May 18 2024 21:37:02",
        "avg_grade": 83.98,
        "score": 87.16,
        "link": "https://www.basketball-reference.com/teams/2021/IND.html",
        "rank": 17
    },
    "WAS": {
        "Tm": "WAS",
        "RRK": "17",
        "Name": "Washington Wizards",
        "img": "https://cdn.ssref.net/req/202312151/tlogo/bbr/WAS-2021.png",
        "standing": "Finished in East in 2021 in East",
        "last_update": "May 18 2024 21:37:02",
        "avg_grade": 80.88,
        "score": 86.55,
        "link": "https://www.basketball-reference.com/teams/2021/WAS.html",
        "rank": 18
    },
    "CHO": {
        "Tm": "CHO",
        "RRK": "19",
        "Name": "Charlotte Hornets",
        "img": "https://cdn.ssref.net/req/202312151/tlogo/bbr/CHO-2021.png",
        "standing": "Finished in East",
        "last_update": "May 18 2024 21:37:02",
        "avg_grade": 81.7,
        "score": 85.98,
        "link": "https://www.basketball-reference.com/teams/2021/CHO.html",
        "rank": 19
    },
    "CHI": {
        "Tm": "CHI",
        "RRK": "21",
        "Name": "Chicago Bulls",
        "img": "https://cdn.ssref.net/req/202312151/tlogo/bbr/CHI-2021.png",
        "standing": "Finished in East",
        "last_update": "May 18 2024 21:37:02",
        "avg_grade": 83.55,
        "score": 85.77,
        "link": "https://www.basketball-reference.com/teams/2021/CHI.html",
        "rank": 20
    },
    "SAS": {
        "Tm": "SAS",
        "RRK": "20",
        "Name": "San Antonio Spurs",
        "img": "https://cdn.ssref.net/req/202312151/tlogo/bbr/SAS-2021.png",
        "standing": "Finished in West",
        "last_update": "May 18 2024 21:37:02",
        "avg_grade": 81.0,
        "score": 85.33,
        "link": "https://www.basketball-reference.com/teams/2021/SAS.html",
        "rank": 21
    },
    "NOP": {
        "Tm": "NOP",
        "RRK": "22",
        "Name": "New Orleans Pelicans",
        "img": "https://cdn.ssref.net/req/202312151/tlogo/bbr/NOP-2021.png",
        "standing": "Finished in West",
        "last_update": "May 18 2024 21:37:02",
        "avg_grade": 81.62,
        "score": 84.71,
        "link": "https://www.basketball-reference.com/teams/2021/NOP.html",
        "rank": 22
    },
    "SAC": {
        "Tm": "SAC",
        "RRK": "23",
        "Name": "Sacramento Kings",
        "img": "https://cdn.ssref.net/req/202312151/tlogo/bbr/SAC-2021.png",
        "standing": "Finished in West",
        "last_update": "May 18 2024 21:37:02",
        "avg_grade": 81.21,
        "score": 84.15,
        "link": "https://www.basketball-reference.com/teams/2021/SAC.html",
        "rank": 23
    },
    "TOR": {
        "Tm": "TOR",
        "RRK": "24",
        "Name": "Toronto Raptors",
        "img": "https://cdn.ssref.net/req/202312151/tlogo/bbr/TOR-2021.png",
        "standing": "Finished in East",
        "last_update": "May 18 2024 21:37:02",
        "avg_grade": 81.78,
        "score": 83.93,
        "link": "https://www.basketball-reference.com/teams/2021/TOR.html",
        "rank": 24
    },
    "MIN": {
        "Tm": "MIN",
        "RRK": "25",
        "Name": "Minnesota Timberwolves",
        "img": "https://cdn.ssref.net/req/202312151/tlogo/bbr/MIN-2021.png",
        "standing": "Finished in West",
        "last_update": "May 18 2024 21:37:02",
        "avg_grade": 77.87,
        "score": 82.21,
        "link": "https://www.basketball-reference.com/teams/2021/MIN.html",
        "rank": 25
    },
    "OKC": {
        "Tm": "OKC",
        "RRK": "27",
        "Name": "Oklahoma City Thunder",
        "img": "https://cdn.ssref.net/req/202312151/tlogo/bbr/OKC-2021.png",
        "standing": "Finished in West",
        "last_update": "May 18 2024 21:37:02",
        "avg_grade": 79.42,
        "score": 81.89,
        "link": "https://www.basketball-reference.com/teams/2021/OKC.html",
        "rank": 26
    },
    "CLE": {
        "Tm": "CLE",
        "RRK": "26",
        "Name": "Cleveland Cavaliers",
        "img": "https://cdn.ssref.net/req/202312151/tlogo/bbr/CLE-2021.png",
        "standing": "Finished in East",
        "last_update": "May 18 2024 21:37:02",
        "avg_grade": 76.65,
        "score": 81.38,
        "link": "https://www.basketball-reference.com/teams/2021/CLE.html",
        "rank": 27
    },
    "DET": {
        "Tm": "DET",
        "RRK": "29",
        "Name": "Detroit Pistons",
        "img": "https://cdn.ssref.net/req/202312151/tlogo/bbr/DET-2021.png",
        "standing": "Finished in East",
        "last_update": "May 18 2024 21:37:02",
        "avg_grade": 77.51,
        "score": 80.42,
        "link": "https://www.basketball-reference.com/teams/2021/DET.html",
        "rank": 28
    },
    "HOU": {
        "Tm": "HOU",
        "RRK": "30",
        "Name": "Houston Rockets",
        "img": "https://cdn.ssref.net/req/202312151/tlogo/bbr/HOU-2021.png",
        "standing": "Finished in West",
        "last_update": "May 18 2024 21:37:02",
        "avg_grade": 78.27,
        "score": 80.26,
        "link": "https://www.basketball-reference.com/teams/2021/HOU.html",
        "rank": 29
    },
    "ORL": {
        "Tm": "ORL",
        "RRK": "28",
        "Name": "Orlando Magic",
        "img": "https://cdn.ssref.net/req/202312151/tlogo/bbr/ORL-2021.png",
        "standing": "Finished in East",
        "last_update": "May 18 2024 21:37:02",
        "avg_grade": 74.02,
        "score": 79.67,
        "link": "https://www.basketball-reference.com/teams/2021/ORL.html",
        "rank": 30
    }
}