{
    "NYK": {
        "info": {
            "record": "21-58",
            "standing": "Finished in East",
            "coach": "Carl Braun (21-58)",
            "gm": "Vince Boryla"
        },
        "players": [
            "Whitey Bell",
            "Carl Braun",
            "Dave Budd",
            "Mike Farmer",
            "Dick Garmaker",
            "Jack George",
            "Johnny Green",
            "Richie Guerin",
            "Darrall Imhoff",
            "Phil Jordon",
            "Bob McNeill",
            "Willie Naulls",
            "Jim Palmer",
            "Phil Rollins",
            "Kenny Sears",
            "Charlie Tyra"
        ],
        "injuries": [],
        "team_stats": {
            "Team": {
                "G": "79",
                "MP": "",
                "FG": "3422",
                "FGA": "8347",
                "FG%": ".410",
                "FT": "2135",
                "FTA": "2838",
                "FT%": ".752",
                "ORB": "",
                "DRB": "",
                "TRB": "5315",
                "AST": "1822",
                "PF": "2223",
                "PTS": "8979"
            },
            "Team/G": {
                "G": "",
                "MP": "",
                "FG": "43.3",
                "FGA": "105.7",
                "FG%": ".410",
                "FT": "27.0",
                "FTA": "35.9",
                "FT%": ".752",
                "ORB": "",
                "DRB": "",
                "TRB": "67.3",
                "AST": "23.1",
                "PF": "28.1",
                "PTS": "113.7"
            },
            "Lg Rank": {
                "G": "",
                "MP": "",
                "FG": "7",
                "FGA": "7",
                "FG%": "6",
                "FT": "5",
                "FTA": "6",
                "FT%": "2",
                "ORB": "",
                "DRB": "",
                "TRB": "8",
                "AST": "6",
                "PF": "7",
                "PTS": "8"
            },
            "Year/Year": {
                "G": "",
                "MP": "",
                "FG": "-5.3%",
                "FGA": "-2.8%",
                "FG%": "-.011",
                "FT": "4.4%",
                "FTA": "6.1%",
                "FT%": "-.013",
                "ORB": "",
                "DRB": "",
                "TRB": "-3.9%",
                "AST": "3.8%",
                "PF": "8.8%",
                "PTS": "-3.1%"
            },
            "Opponent": {
                "G": "79",
                "MP": "",
                "FG": "",
                "FGA": "",
                "FG%": "",
                "FT": "",
                "FTA": "",
                "FT%": "",
                "ORB": "",
                "DRB": "",
                "TRB": "",
                "AST": "",
                "PF": "",
                "PTS": "9486"
            },
            "Opponent/G": {
                "G": "",
                "MP": "",
                "FG": "",
                "FGA": "",
                "FG%": "",
                "FT": "",
                "FTA": "",
                "FT%": "",
                "ORB": "",
                "DRB": "",
                "TRB": "",
                "AST": "",
                "PF": "",
                "PTS": "120.1"
            },
            "Opp Lg Rank": {
                "G": "",
                "MP": "",
                "FG": "",
                "FGA": "",
                "FG%": "",
                "FT": "",
                "FTA": "",
                "FT%": "",
                "ORB": "",
                "DRB": "",
                "TRB": "",
                "AST": "",
                "PF": "",
                "PTS": "6"
            },
            "Opp Year/Year": {
                "G": "",
                "MP": "",
                "FG": "",
                "FGA": "",
                "FG%": "",
                "FT": "",
                "FTA": "",
                "FT%": "",
                "ORB": "",
                "DRB": "",
                "TRB": "",
                "AST": "",
                "PF": "",
                "PTS": "0.4%"
            },
            "Misc Team": {
                "W": "21",
                "L": "58",
                "PW": "25",
                "PL": "54",
                "MOV": "-6.42",
                "SOS": "0.99",
                "SRS": "-5.43",
                "ORtg": "91.9",
                "DRtg": "97.1",
                "Pace": "122.9",
                "FTr": ".340",
                "3PAr": "",
                "eFG%": "",
                "TOV%": "",
                "ORB%": "",
                "FT/FGA": "",
                "DRB%": "",
                "Arena": "Madison Square Garden (III)",
                "Attendance": ""
            },
            "Misc Lg Rank": {
                "W": "8",
                "L": "1",
                "PW": "8",
                "PL": "8",
                "MOV": "8",
                "SOS": "1",
                "SRS": "8",
                "ORtg": "4",
                "DRtg": "7",
                "Pace": "7",
                "FTr": "4",
                "3PAr": "",
                "eFG%": "",
                "TOV%": "",
                "ORB%": "",
                "FT/FGA": "",
                "DRB%": "",
                "Arena": "",
                "Attendance": ""
            }
        },
        "image_url": "https://cdn.ssref.net/req/202404172/tlogo/bbr/NYK-1961.png",
        "last_update": "May 18 2024 16:50:06"
    }
}