{
    "ATL": {
        "info": {
            "record": "39-42",
            "standing": "8th in East",
            "coach": "Quin Snyder (39-42)",
            "gm": "Landry Fields",
            "preseason_odds": "+15000"
        },
        "players": [
            "Trae Young",
            "Dyson Daniels",
            "Onyeka Okongwu",
            "Zaccharie Risacher",
            "Vit Krejci",
            "Clint Capela",
            "Garrison Mathews",
            "Jalen Johnson",
            "Dominick Barlow",
            "Mouhamed Gueye",
            "Keaton Wallace",
            "Terance Mann",
            "Georges Niang",
            "Caris LeVert",
            "Larry Nance Jr.",
            "Kobe Bufkin",
            "Daeqwon Plowden",
            "Jacob Toppin"
        ],
        "injuries": [
            {
                "Player": "Kobe Bufkin",
                "Team": "Atlanta Hawks",
                "Update": "Wed, Dec 18, 2024",
                "Description": "Out For Season (Shoulder) - The Hawks said on Wednesday (Dec. 18) that Bufkin will undergo surgery to address a right shoulder instability and will miss the rest of the season."
            },
            {
                "Player": "Clint Capela",
                "Team": "Atlanta Hawks",
                "Update": "Fri, Mar 21, 2025",
                "Description": "Out (Hand) - The Hawks announced on Friday (Mar. 21) that Capela has been diagnosed with a ligament injury in the fourth metacarpal of his left hand. He will be re-evaluated in approximately three-to-four weeks."
            },
            {
                "Player": "Jalen Johnson",
                "Team": "Atlanta Hawks",
                "Update": "Wed, Jan 29, 2025",
                "Description": "Out For Season (Shoulder) - Johnson was diagnosed on Wednesday (Jan. 29) with a torn labrum in his left shoulder and will miss the rest of the season, league sources tell NBA reporter Chris Haynes."
            },
            {
                "Player": "Larry Nance Jr.",
                "Team": "Atlanta Hawks",
                "Update": "Wed, Mar 26, 2025",
                "Description": "Out For Season (Knee) - The Hawks announced on Wednesday (Mar. 27) that Nance Jr. will miss the rest of the season while recovering from a right medial femoral condyle fracture."
            },
            {
                "Player": "Jacob Toppin",
                "Team": "Atlanta Hawks",
                "Update": "Fri, Apr 11, 2025",
                "Description": "Day To Day (Calf) - Toppin did not play on Friday (Apr. 11) against the 76ers."
            }
        ],
        "team_stats": {
            "Team": {
                "G": "81",
                "MP": "19540",
                "FG": "3509",
                "FGA": "7440",
                "FG%": ".472",
                "3P": "1090",
                "3PA": "3049",
                "3P%": ".357",
                "2P": "2419",
                "2PA": "4391",
                "2P%": ".551",
                "FT": "1466",
                "FTA": "1890",
                "FT%": ".776",
                "ORB": "965",
                "DRB": "2640",
                "TRB": "3605",
                "AST": "2394",
                "STL": "790",
                "BLK": "417",
                "TOV": "1257",
                "PF": "1549",
                "PTS": "9574"
            },
            "Team/G": {
                "G": "",
                "MP": "241.2",
                "FG": "43.3",
                "FGA": "91.9",
                "FG%": ".472",
                "3P": "13.5",
                "3PA": "37.6",
                "3P%": ".357",
                "2P": "29.9",
                "2PA": "54.2",
                "2P%": ".551",
                "FT": "18.1",
                "FTA": "23.3",
                "FT%": ".776",
                "ORB": "11.9",
                "DRB": "32.6",
                "TRB": "44.5",
                "AST": "29.6",
                "STL": "9.8",
                "BLK": "5.1",
                "TOV": "15.5",
                "PF": "19.1",
                "PTS": "118.2"
            },
            "Lg Rank": {
                "G": "",
                "MP": "12",
                "FG": "7",
                "FGA": "5",
                "FG%": "14",
                "3P": "14",
                "3PA": "15",
                "3P%": "18",
                "2P": "8",
                "2PA": "9",
                "2P%": "14",
                "FT": "3",
                "FTA": "2",
                "FT%": "18",
                "ORB": "9",
                "DRB": "22",
                "TRB": "14",
                "AST": "2",
                "STL": "2",
                "BLK": "11",
                "TOV": "26",
                "PF": "22",
                "PTS": "5"
            },
            "Year/Year": {
                "G": "",
                "MP": "-0.4%",
                "FG": "0.7%",
                "FGA": "-0.7%",
                "FG%": "+.006",
                "3P": "-1.9%",
                "3PA": "-0.2%",
                "3P%": "-.006",
                "2P": "1.9%",
                "2PA": "-1.0%",
                "2P%": "+.016",
                "FT": "-2.4%",
                "FTA": "0.4%",
                "FT%": "-.022",
                "ORB": "-4.6%",
                "DRB": "1.3%",
                "TRB": "-0.4%",
                "AST": "11.2%",
                "STL": "30.0%",
                "BLK": "14.4%",
                "TOV": "14.6%",
                "PF": "3.0%",
                "PTS": "-0.1%"
            },
            "Opponent": {
                "G": "81",
                "MP": "19540",
                "FG": "3522",
                "FGA": "7310",
                "FG%": ".482",
                "3P": "1154",
                "3PA": "3063",
                "3P%": ".377",
                "2P": "2368",
                "2PA": "4247",
                "2P%": ".558",
                "FT": "1481",
                "FTA": "1843",
                "FT%": ".804",
                "ORB": "833",
                "DRB": "2704",
                "TRB": "3537",
                "AST": "2290",
                "STL": "744",
                "BLK": "398",
                "TOV": "1300",
                "PF": "1555",
                "PTS": "9679"
            },
            "Opponent/G": {
                "G": "",
                "MP": "241.2",
                "FG": "43.5",
                "FGA": "90.2",
                "FG%": ".482",
                "3P": "14.2",
                "3PA": "37.8",
                "3P%": ".377",
                "2P": "29.2",
                "2PA": "52.4",
                "2P%": ".558",
                "FT": "18.3",
                "FTA": "22.8",
                "FT%": ".804",
                "ORB": "10.3",
                "DRB": "33.4",
                "TRB": "43.7",
                "AST": "28.3",
                "STL": "9.2",
                "BLK": "4.9",
                "TOV": "16.0",
                "PF": "19.2",
                "PTS": "119.5"
            },
            "Opp Lg Rank": {
                "G": "",
                "MP": "12",
                "FG": "25",
                "FGA": "20",
                "FG%": "28",
                "3P": "23",
                "3PA": "16",
                "3P%": "28",
                "2P": "24",
                "2PA": "21",
                "2P%": "25",
                "FT": "24",
                "FTA": "23",
                "FT%": "30",
                "ORB": "5",
                "DRB": "18",
                "TRB": "13",
                "AST": "25",
                "STL": "28",
                "BLK": "15",
                "TOV": "3",
                "PF": "8",
                "PTS": "27"
            },
            "Opp Year/Year": {
                "G": "",
                "MP": "-0.4%",
                "FG": "-2.6%",
                "FGA": "0.1%",
                "FG%": "-.013",
                "3P": "1.9%",
                "3PA": "3.8%",
                "3P%": "-.007",
                "2P": "-4.6%",
                "2PA": "-2.4%",
                "2P%": "-.012",
                "FT": "5.8%",
                "FTA": "4.2%",
                "FT%": "+.012",
                "ORB": "-3.1%",
                "DRB": "-0.7%",
                "TRB": "-1.3%",
                "AST": "0.2%",
                "STL": "18.1%",
                "BLK": "-12.6%",
                "TOV": "13.6%",
                "PF": "-1.2%",
                "PTS": "-0.8%"
            },
            "Misc Team": {
                "W": "39",
                "L": "42",
                "PW": "37",
                "PL": "44",
                "MOV": "-1.30",
                "SOS": "-0.27",
                "SRS": "-1.57",
                "ORtg": "114.5",
                "DRtg": "115.8",
                "Pace": "102.7",
                "FTr": ".254",
                "3PAr": ".410",
                "eFG%": ".561",
                "TOV%": "13.8",
                "ORB%": "26.3",
                "FT/FGA": ".203",
                "DRB%": "76.0",
                "Arena": "State Farm Arena",
                "Attendance": "639,899"
            },
            "Misc Lg Rank": {
                "W": "16",
                "L": "13",
                "PW": "19",
                "PL": "19",
                "MOV": "19",
                "SOS": "23",
                "SRS": "19",
                "ORtg": "18",
                "DRtg": "18",
                "Pace": "3",
                "FTr": "8",
                "3PAr": "19",
                "eFG%": "28",
                "TOV%": "5",
                "ORB%": "10",
                "FT/FGA": "22",
                "DRB%": "8",
                "Arena": "",
                "Attendance": "30"
            }
        },
        "image_url": "https://cdn.ssref.net/req/202504041/tlogo/bbr/ATL-2025.png",
        "last_update": "Apr 12 2025 22:32:19"
    }
}