{
    "CLE": {
        "info": {
            "record": "35-6",
            "standing": "1st in East",
            "coach": "Kenny Atkinson (35-6)",
            "gm": "Koby Altman",
            "preseason_odds": "+5000"
        },
        "players": [
            "Jarrett Allen",
            "Georges Niang",
            "Darius Garland",
            "Donovan Mitchell",
            "Evan Mobley",
            "Ty Jerome",
            "Caris LeVert",
            "Sam Merrill",
            "Dean Wade",
            "Isaac Okoro",
            "Craig Porter Jr.",
            "Jaylon Tyson",
            "Tristan Thompson",
            "Max Strus",
            "JT Thor",
            "Luke Travers",
            "Emoni Bates"
        ],
        "injuries": [
            {
                "Player": "Evan Mobley",
                "Team": "Cleveland Cavaliers",
                "Update": "Sun, Jan 19, 2025",
                "Description": "Out (Calf) - The Cavaliers listed Mobley as OUT for Monday's (Jan. 20) game against Phoenix."
            },
            {
                "Player": "Isaac Okoro",
                "Team": "Cleveland Cavaliers",
                "Update": "Sun, Jan 19, 2025",
                "Description": "Out (Shoulder) - The Cavaliers listed Okoro as OUT for Monday's (Jan. 20) game against Phoenix."
            }
        ],
        "team_stats": {
            "Team": {
                "G": "41",
                "MP": "9840",
                "FG": "1833",
                "FGA": "3668",
                "FG%": ".500",
                "3P": "660",
                "3PA": "1668",
                "3P%": ".396",
                "2P": "1173",
                "2PA": "2000",
                "2P%": ".587",
                "FT": "680",
                "FTA": "867",
                "FT%": ".784",
                "ORB": "407",
                "DRB": "1397",
                "TRB": "1804",
                "AST": "1195",
                "STL": "342",
                "BLK": "188",
                "TOV": "538",
                "PF": "739",
                "PTS": "5006"
            },
            "Team/G": {
                "G": "",
                "MP": "240.0",
                "FG": "44.7",
                "FGA": "89.5",
                "FG%": ".500",
                "3P": "16.1",
                "3PA": "40.7",
                "3P%": ".396",
                "2P": "28.6",
                "2PA": "48.8",
                "2P%": ".587",
                "FT": "16.6",
                "FTA": "21.1",
                "FT%": ".784",
                "ORB": "9.9",
                "DRB": "34.1",
                "TRB": "44.0",
                "AST": "29.1",
                "STL": "8.3",
                "BLK": "4.6",
                "TOV": "13.1",
                "PF": "18.0",
                "PTS": "122.1"
            },
            "Lg Rank": {
                "G": "",
                "MP": "27",
                "FG": "3",
                "FGA": "14",
                "FG%": "2",
                "3P": "2",
                "3PA": "5",
                "3P%": "1",
                "2P": "11",
                "2PA": "22",
                "2P%": "1",
                "FT": "18",
                "FTA": "19",
                "FT%": "12",
                "ORB": "22",
                "DRB": "7",
                "TRB": "18",
                "AST": "5",
                "STL": "12",
                "BLK": "24",
                "TOV": "3",
                "PF": "8",
                "PTS": "2"
            },
            "Year/Year": {
                "G": "",
                "MP": "-0.6%",
                "FG": "7.0%",
                "FGA": "2.6%",
                "FG%": "+.021",
                "3P": "19.1%",
                "3PA": "10.6%",
                "3P%": "+.028",
                "2P": "1.3%",
                "2PA": "-3.2%",
                "2P%": "+.026",
                "FT": "6.4%",
                "FTA": "3.8%",
                "FT%": "+.020",
                "ORB": "0.9%",
                "DRB": "1.9%",
                "TRB": "1.7%",
                "AST": "4.0%",
                "STL": "13.1%",
                "BLK": "-1.1%",
                "TOV": "-3.2%",
                "PF": "2.9%",
                "PTS": "8.4%"
            },
            "Opponent": {
                "G": "41",
                "MP": "9840",
                "FG": "1693",
                "FGA": "3690",
                "FG%": ".459",
                "3P": "549",
                "3PA": "1503",
                "3P%": ".365",
                "2P": "1144",
                "2PA": "2187",
                "2P%": ".523",
                "FT": "662",
                "FTA": "844",
                "FT%": ".784",
                "ORB": "442",
                "DRB": "1346",
                "TRB": "1788",
                "AST": "1062",
                "STL": "316",
                "BLK": "187",
                "TOV": "611",
                "PF": "773",
                "PTS": "4597"
            },
            "Opponent/G": {
                "G": "",
                "MP": "240.0",
                "FG": "41.3",
                "FGA": "90.0",
                "FG%": ".459",
                "3P": "13.4",
                "3PA": "36.7",
                "3P%": ".365",
                "2P": "27.9",
                "2PA": "53.3",
                "2P%": ".523",
                "FT": "16.1",
                "FTA": "20.6",
                "FT%": ".784",
                "ORB": "10.8",
                "DRB": "32.8",
                "TRB": "43.6",
                "AST": "25.9",
                "STL": "7.7",
                "BLK": "4.6",
                "TOV": "14.9",
                "PF": "18.9",
                "PTS": "112.1"
            },
            "Opp Lg Rank": {
                "G": "",
                "MP": "27",
                "FG": "18",
                "FGA": "21",
                "FG%": "10",
                "3P": "11",
                "3PA": "9",
                "3P%": "22",
                "2P": "17",
                "2PA": "25",
                "2P%": "5",
                "FT": "9",
                "FTA": "9",
                "FT%": "18",
                "ORB": "12",
                "DRB": "13",
                "TRB": "12",
                "AST": "12",
                "STL": "9",
                "BLK": "10",
                "TOV": "13",
                "PF": "15",
                "PTS": "13"
            },
            "Opp Year/Year": {
                "G": "",
                "MP": "-0.6%",
                "FG": "1.9%",
                "FGA": "2.8%",
                "FG%": "-.004",
                "3P": "6.7%",
                "3PA": "8.4%",
                "3P%": "-.006",
                "2P": "-0.3%",
                "2PA": "-0.7%",
                "2P%": "+.002",
                "FT": "-2.9%",
                "FTA": "-2.1%",
                "FT%": "-.006",
                "ORB": "7.4%",
                "DRB": "0.6%",
                "TRB": "2.2%",
                "AST": "2.6%",
                "STL": "0.0%",
                "BLK": "-9.0%",
                "TOV": "9.6%",
                "PF": "0.7%",
                "PTS": "1.7%"
            },
            "Misc Team": {
                "W": "35",
                "L": "6",
                "PW": "31",
                "PL": "10",
                "MOV": "9.98",
                "SOS": "-1.50",
                "SRS": "8.48",
                "ORtg": "121.8",
                "DRtg": "111.8",
                "Pace": "100.3",
                "FTr": ".236",
                "3PAr": ".455",
                "eFG%": ".533",
                "TOV%": "13.1",
                "ORB%": "23.2",
                "FT/FGA": ".179",
                "DRB%": "76.0",
                "Arena": "Rocket Mortgage Fieldhouse",
                "Attendance": "427,504"
            },
            "Misc Lg Rank": {
                "W": "1",
                "L": "30",
                "PW": "3",
                "PL": "2",
                "MOV": "2",
                "SOS": "29",
                "SRS": "2",
                "ORtg": "1",
                "DRtg": "10",
                "Pace": "6",
                "FTr": "21",
                "3PAr": "6",
                "eFG%": "11",
                "TOV%": "14",
                "ORB%": "20",
                "FT/FGA": "9",
                "DRB%": "12",
                "Arena": "",
                "Attendance": "2"
            }
        },
        "image_url": "https://cdn.ssref.net/req/202412261/tlogo/bbr/CLE-2025.png",
        "last_update": "Jan 20 2025 22:32:12"
    }
}