{
    "NYK": {
        "info": {
            "record": "30-52",
            "standing": "Finished in Atlantic",
            "coach": "Jeff Van Gundy (10-9), Don Chaney (20-43)",
            "gm": "Scott Layden",
            "preseason_odds": "+1200"
        },
        "players": [
            "Shandon Anderson",
            "Marcus Camby",
            "Howard Eisley",
            "Othella Harrington",
            "Allan Houston",
            "Mark Jackson",
            "Travis Knight",
            "Lavor Postell",
            "Larry Robinson",
            "Felton Spencer",
            "Latrell Sprewell",
            "Kurt Thomas",
            "Charlie Ward",
            "Clarence Weatherspoon"
        ],
        "injuries": [],
        "team_stats": {
            "Team": {
                "G": "82",
                "MP": "19805",
                "FG": "2817",
                "FGA": "6520",
                "FG%": ".432",
                "3P": "474",
                "3PA": "1344",
                "3P%": ".353",
                "2P": "2343",
                "2PA": "5176",
                "2P%": ".453",
                "FT": "1406",
                "FTA": "1786",
                "FT%": ".787",
                "ORB": "876",
                "DRB": "2458",
                "TRB": "3334",
                "AST": "1720",
                "STL": "558",
                "BLK": "288",
                "TOV": "1192",
                "PF": "1800",
                "PTS": "7514"
            },
            "Team/G": {
                "G": "",
                "MP": "241.5",
                "FG": "34.4",
                "FGA": "79.5",
                "FG%": ".432",
                "3P": "5.8",
                "3PA": "16.4",
                "3P%": ".353",
                "2P": "28.6",
                "2PA": "63.1",
                "2P%": ".453",
                "FT": "17.1",
                "FTA": "21.8",
                "FT%": ".787",
                "ORB": "10.7",
                "DRB": "30.0",
                "TRB": "40.7",
                "AST": "21.0",
                "STL": "6.8",
                "BLK": "3.5",
                "TOV": "14.5",
                "PF": "22.0",
                "PTS": "91.6"
            },
            "Lg Rank": {
                "G": "",
                "MP": "15",
                "FG": "26",
                "FGA": "23",
                "FG%": "25",
                "3P": "9",
                "3PA": "8",
                "3P%": "16",
                "2P": "26",
                "2PA": "24",
                "2P%": "23",
                "FT": "19",
                "FTA": "22",
                "FT%": "3",
                "ORB": "27",
                "DRB": "16",
                "TRB": "26",
                "AST": "21",
                "STL": "25",
                "BLK": "29",
                "TOV": "16",
                "PF": "21",
                "PTS": "24"
            },
            "Year/Year": {
                "G": "",
                "MP": "-0.5%",
                "FG": "2.3%",
                "FGA": "5.2%",
                "FG%": "-.012",
                "3P": "21.2%",
                "3PA": "20.5%",
                "3P%": "+.002",
                "2P": "-0.9%",
                "2PA": "1.8%",
                "2P%": "-.012",
                "FT": "2.3%",
                "FTA": "3.4%",
                "FT%": "-.008",
                "ORB": "13.3%",
                "DRB": "-2.6%",
                "TRB": "1.1%",
                "AST": "13.2%",
                "STL": "2.4%",
                "BLK": "-16.8%",
                "TOV": "0.3%",
                "PF": "-3.4%",
                "PTS": "3.3%"
            },
            "Opponent": {
                "G": "82",
                "MP": "19805",
                "FG": "2924",
                "FGA": "6570",
                "FG%": ".445",
                "3P": "443",
                "3PA": "1256",
                "3P%": ".353",
                "2P": "2481",
                "2PA": "5314",
                "2P%": ".467",
                "FT": "1550",
                "FTA": "2047",
                "FT%": ".757",
                "ORB": "959",
                "DRB": "2540",
                "TRB": "3499",
                "AST": "1762",
                "STL": "686",
                "BLK": "385",
                "TOV": "1103",
                "PF": "1670",
                "PTS": "7841"
            },
            "Opponent/G": {
                "G": "",
                "MP": "241.5",
                "FG": "35.7",
                "FGA": "80.1",
                "FG%": ".445",
                "3P": "5.4",
                "3PA": "15.3",
                "3P%": ".353",
                "2P": "30.3",
                "2PA": "64.8",
                "2P%": ".467",
                "FT": "18.9",
                "FTA": "25.0",
                "FT%": ".757",
                "ORB": "11.7",
                "DRB": "31.0",
                "TRB": "42.7",
                "AST": "21.5",
                "STL": "8.4",
                "BLK": "4.7",
                "TOV": "13.5",
                "PF": "20.4",
                "PTS": "95.6"
            },
            "Opp Lg Rank": {
                "G": "",
                "MP": "15",
                "FG": "10",
                "FGA": "10",
                "FG%": "13",
                "3P": "20",
                "3PA": "20",
                "3P%": "14",
                "2P": "10",
                "2PA": "8",
                "2P%": "17",
                "FT": "21",
                "FTA": "20",
                "FT%": "23",
                "ORB": "8",
                "DRB": "23",
                "TRB": "15",
                "AST": "9",
                "STL": "25",
                "BLK": "7",
                "TOV": "23",
                "PF": "19",
                "PTS": "14"
            },
            "Opp Year/Year": {
                "G": "",
                "MP": "-0.5%",
                "FG": "13.9%",
                "FGA": "6.7%",
                "FG%": "+.028",
                "3P": "-0.4%",
                "3PA": "-0.8%",
                "3P%": "+.001",
                "2P": "16.9%",
                "2PA": "8.6%",
                "2P%": "+.033",
                "FT": "4.9%",
                "FTA": "1.6%",
                "FT%": "+.024",
                "ORB": "10.0%",
                "DRB": "5.0%",
                "TRB": "6.4%",
                "AST": "12.0%",
                "STL": "15.1%",
                "BLK": "13.9%",
                "TOV": "-9.3%",
                "PF": "-4.8%",
                "PTS": "11.1%"
            },
            "Misc Team": {
                "W": "30",
                "L": "52",
                "PW": "29",
                "PL": "53",
                "MOV": "-3.99",
                "SOS": "-0.16",
                "SRS": "-4.15",
                "ORtg": "101.5",
                "DRtg": "105.9",
                "Pace": "89.7",
                "FTr": ".274",
                "3PAr": ".206",
                "eFG%": ".479",
                "TOV%": "12.9",
                "ORB%": "25.6",
                "FT/FGA": ".236",
                "DRB%": "71.9",
                "Arena": "Madison Square Garden (IV)",
                "Attendance": "810,283"
            },
            "Misc Lg Rank": {
                "W": "23",
                "L": "7",
                "PW": "23",
                "PL": "23",
                "MOV": "23",
                "SOS": "16",
                "SRS": "23",
                "ORtg": "25",
                "DRtg": "18",
                "Pace": "21",
                "FTr": "22",
                "3PAr": "8",
                "eFG%": "15",
                "TOV%": "24",
                "ORB%": "27",
                "FT/FGA": "22",
                "DRB%": "9",
                "Arena": "",
                "Attendance": "4"
            }
        },
        "image_url": "https://cdn.ssref.net/req/202404172/tlogo/bbr/NYK-2002.png",
        "last_update": "May 18 2024 21:37:02"
    }
}